PySystemInfo/__init__.py
PySystemInfo/__version__.py
PySystemInfo/main.py
PySystemInfo-1.0.4.dist-info/LICENSE
PySystemInfo-1.0.4.dist-info/METADATA
PySystemInfo-1.0.4.dist-info/WHEEL
PySystemInfo-1.0.4.dist-info/top_level.txt
PySystemInfo-1.0.4.dist-info/RECORD
