Metadata-Version: 2.1
Name: PySystemInfo
Version: 1.0.4
Summary: It s a package that allows you to easily find out the system information of your computer through Python
Home-page: https://github.com/Gaeduck-0908/PySystemInfo
Author: Gaeduck
Author-email: gms8757@naver.com
License: MIT
Keywords: Sysinfo,system,SystemInfo,Python system,Python System info
Classifier: Programming Language :: Python :: 3
Classifier: Programming Language :: Python :: 3.1
Classifier: Programming Language :: Python :: 3.2
Classifier: Programming Language :: Python :: 3.3
Classifier: Programming Language :: Python :: 3.4
Classifier: Programming Language :: Python :: 3.5
Classifier: Programming Language :: Python :: 3.6
Classifier: Programming Language :: Python :: 3.7
Classifier: Programming Language :: Python :: 3.8
Classifier: Programming Language :: Python :: 3.9
Classifier: Programming Language :: Python :: 3.10
Requires-Python: >=3
License-File: LICENSE
Requires-Dist: psutil
Requires-Dist: py-cpuinfo
Requires-Dist: GPUtil
